{
  "version": "1.2.0",
  "exported_at": "2025-10-20T10:31:17.043Z",
  "params": {
    "x0_1": 2,
    "constant1": 1500,
    "b1": -608,
    "b1Base": -608,
    "autoRolloverB1": false,
    "b1_add_option": -913,
    "x0_2": 10,
    "constant2": 1500,
    "b2": 0,
    "b2Base": 0,
    "autoRolloverB2": false,
    "b2_add_option": 0,
    "anchorY6": 3,
    "refConst": 1500,
    "callContracts": 0,
    "premiumCall": 0,
    "putContracts": 0,
    "premiumPut": 0,
    "longEntryPrice": 2,
    "longShares": 0,
    "shortEntryPrice": 0,
    "shortShares": 0,
    "delta1": 0.3,
    "delta2": 1,
    "includePremium": false,
    "biasMode": "real",
    "x1Range": [
      0.1,
      10
    ]
  },
  "toggles": {
    "showY1": false,
    "showY2": false,
    "showY3": true,
    "showY4": false,
    "showY5": true,
    "showY6": true,
    "showY7": false,
    "showY8": false,
    "showY9": false,
    "showY10": false,
    "showY11": false
  }
}
